promptclasses/__init__.py
promptclasses-0.0.1.dist-info/METADATA
promptclasses-0.0.1.dist-info/WHEEL
promptclasses-0.0.1.dist-info/licenses/LICENSE
promptclasses-0.0.1.dist-info/RECORD
