Metadata-Version: 2.4
Name: promptclasses
Version: 0.0.1
Summary: 🌳 | graph-like agents in the most pythonic & fun way possible
Author-email: Hammad Saeed <hvmmad@gmail.com>
License:                                  Apache License
License-File: LICENSE
Requires-Python: >=3.10
Requires-Dist: instructor>=1.7.2
Requires-Dist: litellm>=1.60.8
Requires-Dist: plum-dispatch>=2.5.7
Requires-Dist: toolz>=1.0.0
Requires-Dist: typedload>=2.37
Requires-Dist: uvloop>=0.21.0
Requires-Dist: wrapt>=1.17.2
Provides-Extra: all
Requires-Dist: graphviz; extra == 'all'
Requires-Dist: litellm; extra == 'all'
Requires-Dist: networkx; extra == 'all'
Provides-Extra: graph
Requires-Dist: graphviz; extra == 'graph'
Requires-Dist: networkx; extra == 'graph'
